KarlLab4/full_adder.vhdl
library ieee;
use ieee.std_logic_1164.all;

entity full_adder is
	port
	(
		a : in std_logic; --input 1
		b : in std_logic; --input 2
		carry_in : in std_logic; --input carry
		sum : out std_logic; --sum of a and b
		carry_out : out std_logic --output carry
	);
end full_adder;

architecture behave of full_adder is

begin

	sum <= a xor b xor carry_in; --0 + 1 = 1, 1 + 0 = 1, 1 + 1 = 0 with a carry out, 0 + 0 with a carry = 1
	carry_out <= (a and b) or (carry_in and a) or (carry_in and b); --carry occurs when: a and b are both 1, there is carry and a OR b are 1
	
end behave;

KarlLab4/ALU8bit.vhdl
library ieee;
use ieee.std_logic_1164.all;

entity ALU8bit is
	port
	(
		opcode : in std_logic_vector(1 downto 0); --decides which operation the ALU will execute
		a : in std_logic_vector(7 downto 0); --8 bit input 1
		b : in std_logic_vector(7 downto 0); --8 bit input 2
		result : out std_logic_vector(7 downto 0) --8 bit result
	);
end ALU8bit;

architecture behave of ALU8bit is
component full_adder is
	port
	(
		a : in std_logic; --input 1
		b : in std_logic; --input 2
		carry_in : in std_logic; --input carry
		sum : out std_logic; --sum of a and b
		carry_out : out std_logic --output carry
	);
end component;

signal b_twos: std_logic_vector(7 downto 0); --contains two's complement of input 2 (b) if subtraction operation is selected, if addition is selected, b is not changed
signal carry: std_logic_vector(8 downto 0); --contains the carrys used
signal final: std_logic_vector(7 downto 0); --final result of ALU Operation
signal equal_vector : std_logic_vector(7 downto 0) := "00000000";

begin
 
	carry(0) <= opcode(0); --If the operation is subtraction, this represents the +1 needed for coversion to two's complement
	--this section flips all bits in the second input if the subtraction operation is selected, using xor
	b_twos(0) <= b(0) xor opcode(0); 
	b_twos(1) <= b(1) xor opcode(0);
	b_twos(2) <= b(2) xor opcode(0); 
	b_twos(3) <= b(3) xor opcode(0);
	b_twos(4) <= b(4) xor opcode(0);
	b_twos(5) <= b(5) xor opcode(0);
	b_twos(6) <= b(6) xor opcode(0);
	b_twos(7) <= b(7) xor opcode(0);

	full_adder1: full_adder port map(carry_in=>carry(0),a=>a(0),b=>b_twos(0),sum=>final(0),carry_out=>carry(1));
	full_adder2: full_adder port map(carry_in=>carry(1),a=>a(1),b=>b_twos(1),sum=>final(1),carry_out=>carry(2));
	full_adder3: full_adder port map(carry_in=>carry(2),a=>a(2),b=>b_twos(2),sum=>final(2),carry_out=>carry(3));
	full_adder4: full_adder port map(carry_in=>carry(3),a=>a(3),b=>b_twos(3),sum=>final(3),carry_out=>carry(4));
	full_adder5: full_adder port map(carry_in=>carry(4),a=>a(4),b=>b_twos(4),sum=>final(4),carry_out=>carry(5));
	full_adder6: full_adder port map(carry_in=>carry(5),a=>a(5),b=>b_twos(5),sum=>final(5),carry_out=>carry(6));
	full_adder7: full_adder port map(carry_in=>carry(6),a=>a(6),b=>b_twos(6),sum=>final(6),carry_out=>carry(7));
	full_adder8: full_adder port map(carry_in=>carry(7),a=>a(7),b=>b_twos(7),sum=>final(7),carry_out=>carry(8));

	result <= final when (opcode = "00") or (opcode = "01") else a; --Outputs the result of the ALU's Operation if add or subtract is selected, otherwise the output is A

end behave;

KarlLab4/reg8.vhdl
library ieee;
use ieee.std_logic_1164.all;

entity reg8 is
	port (  
		clk, we : in std_logic;
		d : in std_logic_vector (7 downto 0);
		q : out std_logic_vector (7 downto 0) := "00000000"
	);
end entity reg8;

architecture behave of reg8 is

begin
reg8_process: process (clk, we, d)
	begin
		if rising_edge(clk) then
			if we = '1' then
				q <= d;
			end if;
		end if;
	end process reg8_process;
end architecture behave;

KarlLab4/mux_4to1.vhdl
library ieee;
use ieee.std_logic_1164.all;

entity mux_4to1 is
	port
	(
		input_vector: in std_logic_vector(31 downto 0);
		sel: in std_logic_vector(1 downto 0); 
		rd: out std_logic_vector(7 downto 0)
	);
end mux_4to1;

architecture behave of mux_4to1 is
begin 
	with sel select
		rd <= input_vector(7 downto 0) when "00",
			 input_vector(15 downto 8) when "01",
			 input_vector(23 downto 16) when "10",
			 input_vector(31 downto 24) when "11",
			 input_vector(7 downto 0) when others;
end architecture behave;

KarlLab4/demux_1to4.vhdl
library ieee;
use ieee.std_logic_1164.all;

entity demux_1to4 is
	port
	(
		we: in std_logic;
		sel: in std_logic_vector(1 downto 0);
		output_we: out std_logic_vector(3 downto 0) := (others => '0')
	);
end demux_1to4;

architecture behave of demux_1to4 is
begin
	process(sel, we)
	begin
	output_we <= "0000";
		case sel is
			when "00" => output_we(0) <= we;
			when "01" => output_we(1) <= we;
			when "10" => output_we(2) <= we;
			when "11" => output_we(3) <= we;
			when others => output_we(0) <= we;
		end case;
end process;
end architecture behave;

KarlLab4/reg8n4.vhdl
library ieee;
use ieee.std_logic_1164.all;

entity reg8n4 is
	port (  
		clk, we : in std_logic;
		rs1, rs2 : in std_logic_vector(1 downto 0);	
		ws : in std_logic_vector (1 downto 0);
		wd : in std_logic_vector(7 downto 0);
		rd1,rd2 : out std_logic_vector (7 downto 0)
	);
end entity reg8n4;

architecture structural of reg8n4 is
 
component reg8 is
	port (  
		clk, we : in std_logic;
		d : in std_logic_vector (7 downto 0);
		q : out std_logic_vector (7 downto 0) := "00000000"
	);
end component;

component demux_1to4 is
	port
	(
		we: in std_logic;
		sel: in std_logic_vector(1 downto 0);
		output_we: out std_logic_vector(3 downto 0) := (others => '0')
	);
end component; 

component mux_4to1 
	port
	(
		input_vector: in std_logic_vector(31 downto 0);
		sel: in std_logic_vector(1 downto 0);
		rd: out std_logic_vector(7 downto 0)
	);
end component;

signal we_vector : std_logic_vector(3 downto 0) := (others => '0');
signal output_vector : std_logic_vector(31 downto 0):= (others => '0');

begin
	
	demux : demux_1to4 port map (we => we, sel => ws, output_we => we_vector);
	mux1 : mux_4to1 port map (input_vector => output_vector, sel => rs1, rd => rd1);
	mux2 : mux_4to1 port map (input_vector => output_vector, sel => rs2, rd => rd2);

	reg_1: reg8 port map (d => wd, clk => clk, we => we_vector(0), q => output_vector(7 downto 0));
	reg_2: reg8 port map (d => wd, clk => clk, we => we_vector(1), q => output_vector(15 downto 8));
	reg_3: reg8 port map (d => wd, clk => clk, we => we_vector(2), q => output_vector(23 downto 16));
	reg_4: reg8 port map (d => wd, clk => clk, we => we_vector(3), q => output_vector(31 downto 24));
	
end architecture structural;

KarlLab4/controller.vhdl
library ieee;
use ieee.std_logic_1164.all;

entity controller is
	port
	(
		opcode_input : in std_logic_vector(1 downto 0); --opcode input
		write_enable : out std_logic; 
		ALU_Opcode : out std_logic_vector(1 downto 0); 
		print_enable : out std_logic
	);
end controller;

architecture behave of controller is
begin 
	process(opcode_input)
	begin
		if(opcode_input = "11") then
			write_enable <= '0';
		elsif(opcode_input ="10") then
			write_enable <= '1';
		else
		    write_enable <= '1';
		end if;
		
		if(opcode_input = "00") then
			ALU_Opcode <= "00"; --adding
		elsif (opcode_input = "01") then
			ALU_Opcode <= "01"; --subtracting
		else 
			ALU_Opcode <= "11"; --nothing?
		end if;
		
		if(opcode_input = "11") then
			print_enable <= '1';
		else
			print_enable <= '0';
		end if;
	end process;
	
end architecture behave;

KarlLab4/mux_2to1.vhdl
library ieee;
use ieee.std_logic_1164.all;

entity mux_2to1 is
	port
	(
		load_int: in std_logic_vector(7 downto 0);
		ALU_Output: in std_logic_vector(7 downto 0);
		sel: in std_logic_vector(1 downto 0); 
		wd: out std_logic_vector(7 downto 0)
	);
end mux_2to1;

architecture behave of mux_2to1 is
begin 
	with sel select
		wd <= ALU_Output when "00",
			  ALU_Output when "01",
			  load_int when "10",
			  ALU_Output when "11",
			  ALU_Output when others;
end architecture behave;

KarlLab4/calculator.vhdl
library STD;                       
library ieee;
use ieee.std_logic_1164.all;
use ieee.numeric_std.all;


entity calculator is
	port
	(
		clk : in std_logic;
		instruction : in std_logic_vector(7 downto 0); --opcode input
		print : out std_logic_vector(7 downto 0) --printing output
	);
end calculator;

architecture behave of calculator is

component controller is
port
	(
		opcode_input : in std_logic_vector(1 downto 0); --opcode input
		write_enable : out std_logic; 
		ALU_Opcode : out std_logic_vector(1 downto 0); 
		print_enable : out std_logic
	);
end component;

component ALU8bit is
	port
	(
		opcode : in std_logic_vector(1 downto 0); --decides which operation the ALU will execute
		a : in std_logic_vector(7 downto 0); --8 bit input 1
		b : in std_logic_vector(7 downto 0); --8 bit input 2
		result : out std_logic_vector(7 downto 0) --8 bit result
	);
end component;

component reg8n4 is
	port (  
		clk, we : in std_logic;
		rs1, rs2 : in std_logic_vector(1 downto 0);	
		ws : in std_logic_vector (1 downto 0);
		wd : in std_logic_vector(7 downto 0);
		rd1,rd2 : out std_logic_vector (7 downto 0)
	);
end component;

component mux_2to1 is
	port
	(
		load_int: in std_logic_vector(7 downto 0);
		ALU_Output: in std_logic_vector(7 downto 0);
		sel: in std_logic_vector(1 downto 0); 
		wd: out std_logic_vector(7 downto 0)
	);
end component;

signal write_enable : std_logic := '0';
signal ALU_Opcode : std_logic_vector(1 downto 0);
signal print_enable : std_logic := '0';

signal rd11 : std_logic_vector(7 downto 0);
signal rd22 : std_logic_vector(7 downto 0);

signal ALU_Output : std_logic_vector(7 downto 0);
signal load_or_ALU : std_logic_vector(7 downto 0);

signal sign_extender: std_logic_vector(7 downto 0);


begin
	
	sign_extender <= std_logic_vector(resize(signed(instruction(5 downto 2)), sign_extender'length));

	mux_2to11 : mux_2to1 port map (load_int=>sign_extender,
								   ALU_Output=>ALU_Output,
								   sel=>instruction(7 downto 6),
								   wd=>load_or_ALU);
	
	controller1: controller port map (opcode_input => instruction(7 downto 6), 
									  write_enable => write_enable, 
									  ALU_Opcode => ALU_Opcode, 
									  print_enable => print_enable);
									  
	reg8n41: reg8n4 port map (clk=>clk, 
								 we=>write_enable, 
								 rs1=>instruction(5 downto 4), 
								 rs2=>instruction(3 downto 2),
								 ws=>instruction(1 downto 0),
								 wd=>load_or_ALU,
								 rd1=> rd11,
								 rd2=> rd22);
								 
	ALU8bit1 : ALU8bit port map (opcode=>ALU_Opcode,
								 a=>rd11,
								 b=>rd22,
								 result=>ALU_Output);
								 
	with print_enable select
		print <= ALU_Output when '1', 
				 "00000000" when '0',
			     "00000000" when others;
	
	
	process(instruction)
	begin
		if(print_enable = '1') then
			report integer'image(to_integer(signed(ALU_Output)));
		end if;
	end process;
end behave;

KarlLab4/top_level.vhdl
library IEEE;
use IEEE.STD_LOGIC_1164.ALL;

-- Uncomment the following library declaration if using
-- arithmetic functions with Signed or Unsigned values
use IEEE.NUMERIC_STD.ALL;


-- Uncomment the following library declaration if instantiating
-- any Xilinx leaf cells in this code.
--library UNISIM;
--use UNISIM.VComponents.all;

entity top_level is
    Port ( input : in std_logic_vector(7 downto 0);
		   clk : in std_logic;
		   output : out std_logic_vector(7 downto 0)
		   );
end top_level;

architecture Behavioral of top_level is

component calculator is
port
	(
		clk : in std_logic;
		instruction : in std_logic_vector(7 downto 0); --opcode input
		print : out std_logic_vector(7 downto 0) --printing output
	);
end component;

signal btn : std_logic;

signal inputt : std_logic_vector(7 downto 0);
signal outputt : std_logic_vector(7 downto 0);

begin

inputt <= input; 
calc : calculator port map (clk => clk, instruction => inputt, print => outputt);
output <= outputt;


end Behavioral;

KarlLab4/top_level_tb.vhdl
library ieee;
use ieee.std_logic_1164.all;
use ieee.numeric_std.all;

entity top_level_tb is
end top_level_tb;

architecture behave of top_level_tb is
--  Declaration of the component that will be instantiated.
component top_level
	port
	(
		input : in std_logic_vector(7 downto 0);
		clk : in std_logic;
		output : out std_logic_vector(7 downto 0)
	);
end component;

signal clk: std_logic;
signal input : std_logic_vector(7 downto 0); 
signal output : std_logic_vector(7 downto 0); 

begin

	top_levell: top_level port map (input => input, 
									clk => clk, 
									output => output);
	
process
	type pattern_type is record
	--  The inputs of the reg.
	clk: std_logic;
	input : std_logic_vector(7 downto 0);
	--  The expected outputs of the reg.
	output : std_logic_vector(7 downto 0);
end record; 

type pattern_array is array (natural range <>) of pattern_type;
constant patterns : pattern_array := 
--Instruction Structure:
--OP|rs1|rs2|ws (add(00)/sub(01))
--OP|int|ws (lw)
--OP|rs1|null (print)

--All inputs are done twice to simulate button presses on the FPGA board
(
--clk    Input       Output
('0', "00000000", "00000000"), --add r0 r0 r0
('1', "00000000", "00000000"), 
('0', "10000100", "00000000"), --lw 0001 r0
('1', "10000100", "00000000"), 
('0', "11000000", "00000001"), --pr r0, outputs 1
('1', "11000000", "00000001"), 
('0', "10111101", "00000000"), --lw 1111 r1
('1', "10111101", "00000000"), 
('0', "11010000", "11111111"), --pr r1, outputs -1
('1', "11010000", "11111111"), 
('0', "00000010", "00000000"), --add r0 r0 r2, result 2
('1', "00000010", "00000000"), 
('0', "11100000", "00000010"), --pr r2, outputs 2
('1', "11100000", "00000010"),
('0', "01100011", "00000000"), --sub r2 r0 r3, result 1
('1', "01100011", "00000000"), 
('0', "11110000", "00000001"), --pr r3, outputs 1
('1', "11110000", "00000001"), 
('0', "00010111", "00000000"), --add r1 r1 r4, result -2
('1', "00010111", "00000000"),
('0', "11110000", "11111110"), --pr r3, outputs -2
('1', "11110000", "11111110"), 
('0', "01100111", "00000000"), --sub r2 r1, result 3
('1', "01100111", "00000000"), 
('0', "11110011", "00000011"), --pr r3, outputs 3
('1', "11110011", "00000011"), 
('0', "00000000", "00000000") --empty
); --end of test vectors

begin 
	--  Check each pattern.
	for n in patterns'range loop
		--  Set the inputs.
		clk <= patterns(n).clk;
		input <= patterns(n).input;
		--  Wait for the results.
		wait for 5 ns;
		--  Check the outputs.
		assert output = patterns(n).output
		report "incorrect output" severity error;
		
	end loop;
	assert false report "end of test" severity note;
	--  Wait forever; this will finish the simulation.
	wait;
	end process;
end behave;

KarlLab4/top_level.vcd
$date
  Tue May 23 20:00:40 2023
$end
$version
  GHDL v0
$end
$timescale
  1 fs
$end
$scope module standard $end
$upscope $end
$scope module std_logic_1164 $end
$upscope $end
$scope module numeric_std $end
$upscope $end
$scope module top_level_tb $end
$var reg 1 ! clk $end
$var reg 8 " input[7:0] $end
$var reg 8 # output[7:0] $end
$scope module top_levell $end
$var reg 8 $ input[7:0] $end
$var reg 1 % clk $end
$var reg 8 & output[7:0] $end
$var reg 1 ' btn $end
$var reg 8 ( inputt[7:0] $end
$var reg 8 ) outputt[7:0] $end
$scope module calc $end
$var reg 1 * clk $end
$var reg 8 + instruction[7:0] $end
$var reg 8 , print[7:0] $end
$var reg 1 - write_enable $end
$var reg 2 . alu_opcode[1:0] $end
$var reg 1 / print_enable $end
$var reg 8 0 rd11[7:0] $end
$var reg 8 1 rd22[7:0] $end
$var reg 8 2 alu_output[7:0] $end
$var reg 8 3 load_or_alu[7:0] $end
$var reg 8 4 sign_extender[7:0] $end
$scope module mux_2to11 $end
$var reg 8 5 load_int[7:0] $end
$var reg 8 6 alu_output[7:0] $end
$var reg 2 7 sel[1:0] $end
$var reg 8 8 wd[7:0] $end
$upscope $end
$scope module controller1 $end
$var reg 2 9 opcode_input[1:0] $end
$var reg 1 : write_enable $end
$var reg 2 ; alu_opcode[1:0] $end
$var reg 1 < print_enable $end
$upscope $end
$scope module reg8n41 $end
$var reg 1 = clk $end
$var reg 1 > we $end
$var reg 2 ? rs1[1:0] $end
$var reg 2 @ rs2[1:0] $end
$var reg 2 A ws[1:0] $end
$var reg 8 B wd[7:0] $end
$var reg 8 C rd1[7:0] $end
$var reg 8 D rd2[7:0] $end
$var reg 4 E we_vector[3:0] $end
$var reg 32 F output_vector[31:0] $end
$scope module demux $end
$var reg 1 G we $end
$var reg 2 H sel[1:0] $end
$var reg 4 I output_we[3:0] $end
$upscope $end
$scope module mux1 $end
$var reg 32 J input_vector[31:0] $end
$var reg 2 K sel[1:0] $end
$var reg 8 L rd[7:0] $end
$upscope $end
$scope module mux2 $end
$var reg 32 M input_vector[31:0] $end
$var reg 2 N sel[1:0] $end
$var reg 8 O rd[7:0] $end
$upscope $end
$scope module reg_1 $end
$var reg 1 P clk $end
$var reg 1 Q we $end
$var reg 8 R d[7:0] $end
$var reg 8 S q[7:0] $end
$upscope $end
$scope module reg_2 $end
$var reg 1 T clk $end
$var reg 1 U we $end
$var reg 8 V d[7:0] $end
$var reg 8 W q[7:0] $end
$upscope $end
$scope module reg_3 $end
$var reg 1 X clk $end
$var reg 1 Y we $end
$var reg 8 Z d[7:0] $end
$var reg 8 [ q[7:0] $end
$upscope $end
$scope module reg_4 $end
$var reg 1 \ clk $end
$var reg 1 ] we $end
$var reg 8 ^ d[7:0] $end
$var reg 8 _ q[7:0] $end
$upscope $end
$upscope $end
$scope module alu8bit1 $end
$var reg 2 ` opcode[1:0] $end
$var reg 8 a a[7:0] $end
$var reg 8 b b[7:0] $end
$var reg 8 c result[7:0] $end
$var reg 8 d b_twos[7:0] $end
$var reg 9 e carry[8:0] $end
$var reg 8 f final[7:0] $end
$var reg 8 g equal_vector[7:0] $end
$scope module full_adder1 $end
$var reg 1 h a $end
$var reg 1 i b $end
$var reg 1 j carry_in $end
$var reg 1 k sum $end
$var reg 1 l carry_out $end
$upscope $end
$scope module full_adder2 $end
$var reg 1 m a $end
$var reg 1 n b $end
$var reg 1 o carry_in $end
$var reg 1 p sum $end
$var reg 1 q carry_out $end
$upscope $end
$scope module full_adder3 $end
$var reg 1 r a $end
$var reg 1 s b $end
$var reg 1 t carry_in $end
$var reg 1 u sum $end
$var reg 1 v carry_out $end
$upscope $end
$scope module full_adder4 $end
$var reg 1 w a $end
$var reg 1 x b $end
$var reg 1 y carry_in $end
$var reg 1 z sum $end
$var reg 1 { carry_out $end
$upscope $end
$scope module full_adder5 $end
$var reg 1 | a $end
$var reg 1 } b $end
$var reg 1 !" carry_in $end
$var reg 1 "" sum $end
$var reg 1 #" carry_out $end
$upscope $end
$scope module full_adder6 $end
$var reg 1 $" a $end
$var reg 1 %" b $end
$var reg 1 &" carry_in $end
$var reg 1 '" sum $end
$var reg 1 (" carry_out $end
$upscope $end
$scope module full_adder7 $end
$var reg 1 )" a $end
$var reg 1 *" b $end
$var reg 1 +" carry_in $end
$var reg 1 ," sum $end
$var reg 1 -" carry_out $end
$upscope $end
$scope module full_adder8 $end
$var reg 1 ." a $end
$var reg 1 /" b $end
$var reg 1 0" carry_in $end
$var reg 1 1" sum $end
$var reg 1 2" carry_out $end
$upscope $end
$upscope $end
$upscope $end
$upscope $end
$upscope $end
$enddefinitions $end
#0
0!
b00000000 "
b00000000 #
b00000000 $
0%
b00000000 &
U'
b00000000 (
b00000000 )
0*
b00000000 +
b00000000 ,
1-
b00 .
0/
b00000000 0
b00000000 1
b00000000 2
b00000000 3
b00000000 4
b00000000 5
b00000000 6
b00 7
b00000000 8
b00 9
1:
b00 ;
0<
0=
1>
b00 ?
b00 @
b00 A
b00000000 B
b00000000 C
b00000000 D
b0001 E
b00000000000000000000000000000000 F
1G
b00 H
b0001 I
b00000000000000000000000000000000 J
b00 K
b00000000 L
b00000000000000000000000000000000 M
b00 N
b00000000 O
0P
1Q
b00000000 R
b00000000 S
0T
0U
b00000000 V
b00000000 W
0X
0Y
b00000000 Z
b00000000 [
0\
0]
b00000000 ^
b00000000 _
b00 `
b00000000 a
b00000000 b
b00000000 c
b00000000 d
b000000000 e
b00000000 f
b00000000 g
0h
0i
0j
0k
0l
0m
0n
0o
0p
0q
0r
0s
0t
0u
0v
0w
0x
0y
0z
0{
0|
0}
0!"
0""
0#"
0$"
0%"
0&"
0'"
0("
0)"
0*"
0+"
0,"
0-"
0."
0/"
00"
01"
02"
#5000000
1!
1%
1*
1=
1P
1T
1X
1\
#10000000
0!
b10000100 "
b10000100 $
0%
b10000100 (
0*
b10000100 +
b11 .
b00000001 3
b00000001 4
b00000001 5
b10 7
b00000001 8
b10 9
b11 ;
0=
b01 @
b00000001 B
b01 N
0P
b00000001 R
0T
b00000001 V
0X
b00000001 Z
0\
b00000001 ^
b11 `
b11111111 d
b111111111 e
b00000000 f
1i
1j
1l
1n
1o
0p
1q
1s
1t
0u
1v
1x
1y
0z
1{
1}
1!"
0""
1#"
1%"
1&"
0'"
1("
1*"
1+"
0,"
1-"
1/"
10"
01"
12"
#15000000
1!
1%
1*
b00000001 0
b00000001 2
b00000001 6
1=
b00000001 C
b00000000000000000000000000000001 F
b00000000000000000000000000000001 J
b00000001 L
b00000000000000000000000000000001 M
1P
b00000001 S
1T
1X
1\
b00000001 a
b00000001 c
b00000001 f
1h
1k
#20000000
0!
b11000000 "
b00000001 #
b11000000 $
0%
b00000001 &
b11000000 (
b00000001 )
0*
b11000000 +
b00000001 ,
0-
1/
b00000001 1
b00000000 4
b00000000 5
b11 7
b11 9
0:
1<
0=
0>
b00 @
b00000001 D
b0000 E
0G
b0000 I
b00 N
b00000001 O
0P
0Q
0T
0X
0\
b00000001 b
b11111110 d
b00000000 f
0i
0k
#25000000
1!
1%
1*
1=
1P
1T
1X
1\
#30000000
0!
b10111101 "
b00000000 #
b10111101 $
0%
b00000000 &
b10111101 (
b00000000 )
0*
b10111101 +
b00000000 ,
1-
0/
b00000000 0
b00000000 1
b00000000 2
b11111111 3
b11111111 4
b11111111 5
b00000000 6
b10 7
b11111111 8
b10 9
1:
0<
0=
1>
b11 ?
b11 @
b01 A
b11111111 B
b00000000 C
b00000000 D
b0010 E
1G
b01 H
b0010 I
b11 K
b00000000 L
b11 N
b00000000 O
0P
b11111111 R
0T
1U
b11111111 V
0X
b11111111 Z
0\
b11111111 ^
b00000000 a
b00000000 b
b00000000 c
b11111111 d
b111111111 e
b00000000 f
0h
1i
0k
1l
1o
0p
1q
1t
0u
1v
1y
0z
1{
1!"
0""
1#"
1&"
0'"
1("
1+"
0,"
1-"
10"
01"
12"
#35000000
1!
1%
1*
1=
b00000000000000001111111100000001 F
b00000000000000001111111100000001 J
b00000000000000001111111100000001 M
1P
1T
b11111111 W
1X
1\
#40000000
0!
b11010000 "
b11111111 #
b11010000 $
0%
b11111111 &
b11010000 (
b11111111 )
0*
b11010000 +
b11111111 ,
0-
1/
b11111111 0
b00000001 1
b11111111 2
b11111111 3
b00000100 4
b00000100 5
b11111111 6
b11 7
b11111111 8
b11 9
0:
1<
0=
0>
b01 ?
b00 @
b00 A
b11111111 B
b11111111 C
b00000001 D
b0000 E
0G
b00 H
b0000 I
b01 K
b11111111 L
b00 N
b00000001 O
0P
0Q
b11111111 R
0T
0U
b11111111 V
0X
b11111111 Z
0\
b11111111 ^
b11111111 a
b00000001 b
b11111111 c
b11111110 d
b11111110 f
1h
0i
0k
1m
1p
1r
1u
1w
1z
1|
1""
1$"
1'"
1)"
1,"
1."
11"
#45000000
1!
1%
1*
1=
1P
1T
1X
1\
#50000000
0!
b00000010 "
b00000000 #
b00000010 $
0%
b00000000 &
b00000010 (
b00000000 )
0*
b00000010 +
b00000000 ,
1-
b00 .
0/
b00000001 0
b00000010 2
b00000010 3
b00000000 4
b00000000 5
b00000010 6
b00 7
b00000010 8
b00 9
1:
b00 ;
0<
0=
1>
b00 ?
b10 A
b00000010 B
b00000001 C
b0100 E
1G
b10 H
b0100 I
b00 K
b00000001 L
0P
b00000010 R
0T
b00000010 V
0X
1Y
b00000010 Z
0\
b00000010 ^
b00 `
b00000001 a
b00000010 c
b00000001 d
b000000010 e
b00000010 f
1i
0j
0m
0n
1p
0q
0r
0s
0t
0u
0v
0w
0x
0y
0z
0{
0|
0}
0!"
0""
0#"
0$"
0%"
0&"
0'"
0("
0)"
0*"
0+"
0,"
0-"
0."
0/"
00"
01"
02"
#55000000
1!
1%
1*
1=
b00000000000000101111111100000001 F
b00000000000000101111111100000001 J
b00000000000000101111111100000001 M
1P
1T
1X
b00000010 [
1\
#60000000
0!
b11100000 "
b00000010 #
b11100000 $
0%
b00000010 &
b11100000 (
b00000010 )
0*
b11100000 +
b00000010 ,
0-
b11 .
1/
b00000010 0
b11111000 4
b11111000 5
b11 7
b11 9
0:
b11 ;
1<
0=
0>
b10 ?
b00 A
b00000010 C
b0000 E
0G
b00 H
b0000 I
b10 K
b00000010 L
0P
0Q
0T
0X
0Y
0\
b11 `
b00000010 a
b11111110 d
b111111101 e
b00000001 f
0h
0i
1j
1k
0l
1m
1n
0o
0p
1q
1s
1t
1v
1x
1y
0z
1{
1}
1!"
0""
1#"
1%"
1&"
0'"
1("
1*"
1+"
0,"
1-"
1/"
10"
01"
12"
#65000000
1!
1%
1*
1=
1P
1T
1X
1\
#70000000
0!
b01100011 "
b00000000 #
b01100011 $
0%
b00000000 &
b01100011 (
b00000000 )
0*
b01100011 +
b00000000 ,
1-
b01 .
0/
b00000001 2
b00000001 3
b00000001 6
b01 7
b00000001 8
b01 9
1:
b01 ;
0<
0=
1>
b11 A
b00000001 B
b1000 E
1G
b11 H
b1000 I
0P
b00000001 R
0T
b00000001 V
0X
b00000001 Z
0\
1]
b00000001 ^
b01 `
b00000001 c
#75000000
1!
1%
1*
1=
b00000001000000101111111100000001 F
b00000001000000101111111100000001 J
b00000001000000101111111100000001 M
1P
1T
1X
1\
b00000001 _
#80000000
0!
b11110000 "
b00000001 #
b11110000 $
0%
b00000001 &
b11110000 (
b00000001 )
0*
b11110000 +
b00000001 ,
0-
b11 .
1/
b00000001 0
b11111100 4
b11111100 5
b11 7
b11 9
0:
b11 ;
1<
0=
0>
b11 ?
b00 A
b00000001 C
b0000 E
0G
b00 H
b0000 I
b11 K
b00000001 L
0P
0Q
0T
0X
0\
0]
b11 `
b00000001 a
b111111111 e
b00000000 f
1h
0k
1l
0m
1o
0p
1q
1t
0u
1v
1y
0z
1{
1!"
0""
1#"
1&"
0'"
1("
1+"
0,"
1-"
10"
01"
12"
#85000000
1!
1%
1*
1=
1P
1T
1X
1\
#90000000
0!
b00010111 "
b00000000 #
b00010111 $
0%
b00000000 &
b00010111 (
b00000000 )
0*
b00010111 +
b00000000 ,
1-
b00 .
0/
b11111111 0
b11111111 1
b11111110 2
b11111110 3
b00000101 4
b00000101 5
b11111110 6
b00 7
b11111110 8
b00 9
1:
b00 ;
0<
0=
1>
b01 ?
b01 @
b11 A
b11111110 B
b11111111 C
b11111111 D
b1000 E
1G
b11 H
b1000 I
b01 K
b11111111 L
b01 N
b11111111 O
0P
b11111110 R
0T
b11111110 V
0X
b11111110 Z
0\
1]
b11111110 ^
b00 `
b11111111 a
b11111111 b
b11111110 c
b11111111 d
b111111110 e
b11111110 f
1i
0j
1m
1p
1r
1u
1w
1z
1|
1""
1$"
1'"
1)"
1,"
1."
11"
#95000000
1!
1%
1*
1=
b11111110000000101111111100000001 F
b11111110000000101111111100000001 J
b11111110000000101111111100000001 M
1P
1T
1X
1\
b11111110 _
#100000000
0!
b11110000 "
b11111110 #
b11110000 $
0%
b11111110 &
b11110000 (
b11111110 )
0*
b11110000 +
b11111110 ,
0-
b11 .
1/
b11111110 0
b00000001 1
b11111100 4
b11111100 5
b11 7
b11 9
0:
b11 ;
1<
0=
0>
b11 ?
b00 @
b00 A
b11111110 C
b00000001 D
b0000 E
0G
b00 H
b0000 I
b11 K
b11111110 L
b00 N
b00000001 O
0P
0Q
0T
0X
0\
0]
b11 `
b11111110 a
b00000001 b
b11111110 d
b111111101 e
b11111101 f
0h
0i
1j
1k
0l
0o
0p
#105000000
1!
1%
1*
1=
1P
1T
1X
1\
#110000000
0!
b01100111 "
b00000000 #
b01100111 $
0%
b00000000 &
b01100111 (
b00000000 )
0*
b01100111 +
b00000000 ,
1-
b01 .
0/
b00000010 0
b11111111 1
b00000011 2
b00000011 3
b11111001 4
b11111001 5
b00000011 6
b01 7
b00000011 8
b01 9
1:
b01 ;
0<
0=
1>
b10 ?
b01 @
b11 A
b00000011 B
b00000010 C
b11111111 D
b1000 E
1G
b11 H
b1000 I
b10 K
b00000010 L
b01 N
b11111111 O
0P
b00000011 R
0T
b00000011 V
0X
b00000011 Z
0\
1]
b00000011 ^
b01 `
b00000010 a
b11111111 b
b00000011 c
b00000000 d
b000000001 e
b00000011 f
0n
1p
0q
0r
0s
0t
0u
0v
0w
0x
0y
0z
0{
0|
0}
0!"
0""
0#"
0$"
0%"
0&"
0'"
0("
0)"
0*"
0+"
0,"
0-"
0."
0/"
00"
01"
02"
#115000000
1!
1%
1*
1=
b00000011000000101111111100000001 F
b00000011000000101111111100000001 J
b00000011000000101111111100000001 M
1P
1T
1X
1\
b00000011 _
#120000000
0!
b11110011 "
b00000011 #
b11110011 $
0%
b00000011 &
b11110011 (
b00000011 )
0*
b11110011 +
b00000011 ,
0-
b11 .
1/
b00000011 0
b00000001 1
b11111100 4
b11111100 5
b11 7
b11 9
0:
b11 ;
1<
0=
0>
b11 ?
b00 @
b00000011 C
b00000001 D
b0000 E
0G
b0000 I
b11 K
b00000011 L
b00 N
b00000001 O
0P
0T
0X
0\
0]
b11 `
b00000011 a
b00000001 b
b11111110 d
b111111111 e
b00000010 f
1h
0k
1l
1n
1o
1q
1s
1t
0u
1v
1x
1y
0z
1{
1}
1!"
0""
1#"
1%"
1&"
0'"
1("
1*"
1+"
0,"
1-"
1/"
10"
01"
12"
#125000000
1!
1%
1*
1=
1P
1T
1X
1\
#130000000
0!
b00000000 "
b00000000 #
b00000000 $
0%
b00000000 &
b00000000 (
b00000000 )
0*
b00000000 +
b00000000 ,
1-
b00 .
0/
b00000001 0
b00000010 2
b00000010 3
b00000000 4
b00000000 5
b00000010 6
b00 7
b00000010 8
b00 9
1:
b00 ;
0<
0=
1>
b00 ?
b00 A
b00000010 B
b00000001 C
b0001 E
1G
b00 H
b0001 I
b00 K
b00000001 L
0P
1Q
b00000010 R
0T
b00000010 V
0X
b00000010 Z
0\
b00000010 ^
b00 `
b00000001 a
b00000010 c
b00000001 d
b000000010 e
b00000010 f
1i
0j
0m
0n
1p
0q
0s
0t
0u
0v
0x
0y
0z
0{
0}
0!"
0""
0#"
0%"
0&"
0'"
0("
0*"
0+"
0,"
0-"
0/"
00"
01"
02"
